tf_idf/__init__.py
tf_idf/_modidx.py
tf_idf/core.py
tf_idf_cosimm-0.0.2.dist-info/LICENSE
tf_idf_cosimm-0.0.2.dist-info/METADATA
tf_idf_cosimm-0.0.2.dist-info/WHEEL
tf_idf_cosimm-0.0.2.dist-info/entry_points.txt
tf_idf_cosimm-0.0.2.dist-info/top_level.txt
tf_idf_cosimm-0.0.2.dist-info/RECORD
