Metadata-Version: 2.1
Name: tf_idf_cosimm
Version: 0.0.2
Summary: This is a short set of functions meant to help analyze cosine similarity between texts
Home-page: https://github.com/cooperrc/tf_idf_cosimm
Author: Ryan C. Cooper
Author-email: ryan.c.cooper@uconn.edu
License: Apache Software License 2.0
Keywords: nbdev jupyter notebook python
Classifier: Development Status :: 4 - Beta
Classifier: Intended Audience :: Developers
Classifier: Natural Language :: English
Classifier: Programming Language :: Python :: 3.7
Classifier: Programming Language :: Python :: 3.8
Classifier: Programming Language :: Python :: 3.9
Classifier: Programming Language :: Python :: 3.10
Classifier: License :: OSI Approved :: Apache Software License
Requires-Python: >=3.7
License-File: LICENSE
Requires-Dist: numpy
Requires-Dist: pandas
Requires-Dist: nltk
Requires-Dist: scikit-learn
Provides-Extra: dev
